df_pipeline/__init__.py
df_pipeline/conditions.py
df_pipeline/messenger_interface.py
df_pipeline/types.py
df_pipeline/pipeline/__init__.py
df_pipeline/pipeline/component.py
df_pipeline/pipeline/pipeline.py
df_pipeline/pipeline/utils.py
df_pipeline/service/__init__.py
df_pipeline/service/group.py
df_pipeline/service/service.py
df_pipeline/service/utils.py
df_pipeline/service/wrapper.py
df_pipeline-0.3.0.dist-info/LICENSE
df_pipeline-0.3.0.dist-info/METADATA
df_pipeline-0.3.0.dist-info/WHEEL
df_pipeline-0.3.0.dist-info/top_level.txt
df_pipeline-0.3.0.dist-info/RECORD
