Metadata-Version: 2.1
Name: df-pipeline
Version: 0.3.0
Summary: **Dialog Flow Pipeline** is python module add-on for [Dialog Flow Framework](https://github.com/deepmipt/dialog_flow_framework), a free and open-source software stack for creating chatbots, released under the terms of Apache License 2.0.
Home-page: https://github.com/deepmipt/dialog_flow_pipeline
Author: Denis Kuznetsov
Author-email: kuznetsov.den.p@gmail.com
Keywords: chatbots,Dialog Flow Pipeline
Classifier: Development Status :: 2 - Pre-Alpha
Classifier: Intended Audience :: Developers
Classifier: Topic :: Software Development :: Build Tools
Classifier: License :: OSI Approved :: Apache Software License
Classifier: Operating System :: OS Independent
Classifier: Programming Language :: Python :: 3
Classifier: Programming Language :: Python :: 3.6
Classifier: Programming Language :: Python :: 3.7
Classifier: Programming Language :: Python :: 3.8
Classifier: Programming Language :: Python :: 3.9
Classifier: Programming Language :: Python :: 3 :: Only
Requires-Python: >=3.6, <4
License-File: LICENSE
Requires-Dist: df-engine (>=0.9.0)
Requires-Dist: df-db-connector (>=0.1.1)
Requires-Dist: nest-asyncio (>=1.5.5)
Requires-Dist: typing-extensions (>=4.0.0)
